diagrams_adapters/__init__.py
diagrams_adapters/typings.py
diagrams_adapters/processors/__init__.py
diagrams_adapters/processors/base.py
diagrams_adapters/processors/json.py
diagrams_adapters-1.0.1.dist-info/LICENSE
diagrams_adapters-1.0.1.dist-info/METADATA
diagrams_adapters-1.0.1.dist-info/WHEEL
diagrams_adapters-1.0.1.dist-info/top_level.txt
diagrams_adapters-1.0.1.dist-info/RECORD
