Metadata-Version: 2.1
Name: diagrams-adapters
Version: 1.0.1
Summary: Set of adapters to generate architecture diagrams from popular text file formats.
Home-page: https://github.com/TamoshaytisV/diagrams-adapters
Author: Vladas Tamošaitis
Author-email: amd.vladas@gmail.com
License: MIT
Platform: UNKNOWN
Classifier: License :: OSI Approved :: MIT License
Classifier: Operating System :: OS Independent
Classifier: Programming Language :: Python :: 3.6
Classifier: Programming Language :: Python :: 3.7
Classifier: Programming Language :: Python :: 3.8
Classifier: Programming Language :: Python :: Implementation :: CPython
Classifier: Programming Language :: Python :: Implementation :: PyPy
Requires-Python: >=3.6
Requires-Dist: diagrams
Requires-Dist: typing-extensions ; python_version < "3.8.0"
